CHANGES.txt
DEPENDENCES.txt
README.txt
setup.py
design/index.html
design/style.css
design/images/contentbottomleft.gif
design/images/contentbottomright.gif
design/images/contenttopleft.gif
design/images/contenttopright.gif
design/images/footerbg.gif
design/images/footerleft.gif
design/images/footerright.gif
design/images/header.gif
design/images/headerbg.gif
design/images/headerleft.gif
design/images/headerright.gif
design/images/logo.gif
design/images/menuitembg.gif
design/images/menuitemleft.gif
design/images/menuitemright.gif
design/images/project1.gif
design/images/project2.gif
design/images/projectblockbg.gif
design/images/projectblockbottom.gif
design/images/projectblocktop.gif
design/images/searchblockbg.gif
src/ng/__init__.py
src/ng.skin.npclider.egg-info/PKG-INFO
src/ng.skin.npclider.egg-info/SOURCES.txt
src/ng.skin.npclider.egg-info/dependency_links.txt
src/ng.skin.npclider.egg-info/namespace_packages.txt
src/ng.skin.npclider.egg-info/not-zip-safe
src/ng.skin.npclider.egg-info/requires.txt
src/ng.skin.npclider.egg-info/top_level.txt
src/ng/skin/__init__.py
src/ng/skin/npclider/__init__.py
src/ng/skin/npclider/configure.zcml
src/ng/skin/npclider/interfaces.py
src/ng/skin/npclider/ng.skin.npclider.txt
src/ng/skin/npclider/orderinformation.py
src/ng/skin/npclider/roundedcorner.pt
src/ng/skin/npclider/skeleton.pt
src/ng/skin/npclider/style.css
src/ng/skin/npclider/style_form.css
src/ng/skin/npclider/style_ie.css
src/ng/skin/npclider/style_print.css
src/ng/skin/npclider/etc/ng.skin.npclider-configure.zcml
src/ng/skin/npclider/images/abstractbg.gif
src/ng/skin/npclider/images/articlebg.gif
src/ng/skin/npclider/images/contentbottomleft.gif
src/ng/skin/npclider/images/contentbottomright.gif
src/ng/skin/npclider/images/contenttopleft.gif
src/ng/skin/npclider/images/contenttopright.gif
src/ng/skin/npclider/images/currentboxbg.gif
src/ng/skin/npclider/images/currentboxbottom.gif
src/ng/skin/npclider/images/currentboxtop.gif
src/ng/skin/npclider/images/footerbg.gif
src/ng/skin/npclider/images/footerleft.gif
src/ng/skin/npclider/images/footerright.gif
src/ng/skin/npclider/images/header.gif
src/ng/skin/npclider/images/headerbg.gif
src/ng/skin/npclider/images/headerleft.gif
src/ng/skin/npclider/images/headerright.gif
src/ng/skin/npclider/images/logo.gif
